[
    {
        "userId": "user_000001",
        "settings": {
            "theme": "light",
            "language": "en",
            "layout": "masonry",
            "notifications": {
                "push": true,
                "email": false
            }
        },
        "savedCards": [
            "card_000034",
            "card_000077",
            "card_000012"
        ],
        "collections": [
            "col_000001",
            "col_000002",
            "col_000004",
            "col_000018",
            "col_000019"
        ],
        "cardOrder": {
            "col_000001": [
                "card_000001",
                "card_000010",
                "card_000034"
            ],
            "col_000002": [
                "card_000012",
                "card_000008",
                "card_000011"
            ],
            "col_000004": [
                "card_000015",
                "card_000034"
            ],
            "col_000018": [
                "card_000055",
                "card_000034",
                "card_000056"
            ],
            "col_000019": [
                "card_000060",
                "card_000062"
            ]
        },
        "updatedAt": 1732661000
    },
    {
        "userId": "user_000002",
        "settings": {
            "theme": "dark",
            "language": "en",
            "layout": "square",
            "notifications": {
                "push": false,
                "email": false
            }
        },
        "savedCards": [
            "card_000006",
            "card_000009",
            "card_000073"
        ],
        "collections": [
            "col_000003",
            "col_000005",
            "col_000020",
            "col_000021"
        ],
        "cardOrder": {
            "col_000003": [
                "card_000006",
                "card_000034",
                "card_000007"
            ],
            "col_000005": [
                "card_000009",
                "card_000013"
            ],
            "col_000020": [
                "card_000021",
                "card_000022",
                "card_000024"
            ],
            "col_000021": [
                "card_000073"
            ]
        },
        "updatedAt": 1732661100
    },
    {
        "userId": "user_000003",
        "settings": {
            "theme": "dark",
            "language": "en",
            "layout": "tall",
            "notifications": {
                "push": true,
                "email": false
            }
        },
        "savedCards": [
            "card_000040",
            "card_000041",
            "card_000015"
        ],
        "collections": [
            "col_000006",
            "col_000007",
            "col_000008",
            "col_000022",
            "col_000023",
            "col_000024",
            "col_000025"
        ],
        "cardOrder": {
            "col_000006": [
                "card_000040",
                "card_000041",
                "card_000042"
            ],
            "col_000007": [
                "card_000015",
                "card_000043"
            ],
            "col_000008": [
                "card_000041",
                "card_000003"
            ],
            "col_000022": [
                "card_000048"
            ],
            "col_000023": [
                "card_000049",
                "card_000050",
                "card_000051"
            ],
            "col_000024": [
                "card_000051"
            ],
            "col_000025": [
                "card_000040",
                "card_000042",
                "card_000015"
            ]
        },
        "updatedAt": 1732661200
    },
    {
        "userId": "user_000004",
        "settings": {
            "theme": "light",
            "language": "en",
            "layout": "square",
            "notifications": {
                "push": false,
                "email": true
            }
        },
        "savedCards": [
            "card_000018",
            "card_000019",
            "card_000020",
            "card_000021"
        ],
        "collections": [
            "col_000009",
            "col_000010",
            "col_000011",
            "col_000012"
        ],
        "cardOrder": {
            "col_000009": [
                "card_000018",
                "card_000026"
            ],
            "col_000010": [
                "card_000019",
                "card_000020"
            ],
            "col_000011": [
                "card_000021"
            ],
            "col_000012": []
        },
        "updatedAt": 1732661300
    },
    {
        "userId": "user_000005",
        "settings": {
            "theme": "dark",
            "language": "en",
            "layout": "masonry",
            "notifications": {
                "push": true,
                "email": true
            }
        },
        "savedCards": [
            "card_000030",
            "card_000031"
        ],
        "collections": [
            "col_000013",
            "col_000014",
            "col_000015",
            "col_000016",
            "col_000026",
            "col_000027",
            "col_000028",
            "col_000029"
        ],
        "cardOrder": {
            "col_000013": [
                "card_000030",
                "card_000033"
            ],
            "col_000014": [
                "card_000031"
            ],
            "col_000015": [
                "card_000032"
            ],
            "col_000016": [
                "card_000033",
                "card_000034"
            ],
            "col_000026": [
                "card_000030"
            ],
            "col_000027": [
                "card_000065",
                "card_000066"
            ],
            "col_000028": [
                "card_000067",
                "card_000068"
            ],
            "col_000029": [
                "card_000030",
                "card_000031"
            ]
        },
        "updatedAt": 1732661400
    },
    {
        "userId": "user_000006",
        "settings": {
            "theme": "light",
            "language": "en",
            "layout": "masonry",
            "notifications": {
                "push": true,
                "email": false
            }
        },
        "savedCards": [
            "card_000070",
            "card_000071",
            "card_000072"
        ],
        "collections": [
            "col_000017",
            "col_000030",
            "col_000031",
            "col_000032",
            "col_000033",
            "col_000034"
        ],
        "cardOrder": {
            "col_000017": [
                "card_000070",
                "card_000073"
            ],
            "col_000030": [
                "card_000071",
                "card_000072"
            ],
            "col_000031": [
                "card_000020"
            ],
            "col_000032": [
                "card_000021"
            ],
            "col_000033": [
                "card_000075",
                "card_000076"
            ],
            "col_000034": [
                "card_000076",
                "card_000071"
            ]
        },
        "updatedAt": 1732661500
    },
    {
        "userId": "user_000007",
        "settings": {
            "theme": "dark",
            "language": "en",
            "layout": "vertical",
            "notifications": {
                "push": false,
                "email": true
            }
        },
        "savedCards": [
            "card_000080",
            "card_000081",
            "card_000082",
            "card_000083"
        ],
        "collections": [
            "col_000035"
        ],
        "cardOrder": {
            "col_000035": []
        },
        "updatedAt": 1732661600
    }
]